[{"StationID":"A1","lat":25.048,"lon":25.048,"name":"台北車站","ename":"Taipei Main Station","FirstLast":[{"To":"A21","Time":["06:07","23:07"],"TrainType":1},{"To":"A13","Time":["06:00","23:00"],"TrainType":2}]},{"StationID":"A2","lat":25.054,"lon":25.054,"name":"三重站","ename":"Sanchong Station","FirstLast":[{"To":"A21","Time":["05:58","23:15"],"TrainType":1},{"To":"A1","Time":["06:08","00:17"],"TrainType":1}]},{"StationID":"A3","lat":25.061,"lon":25.061,"name":"新北產業園區站","ename":"New Taipei Industrial Park Station","FirstLast":[{"To":"A21","Time":["06:02","23:19"],"TrainType":1},{"To":"A1","Time":["06:03","00:12"],"TrainType":1},{"To":"A13","Time":["06:09","23:09"],"TrainType":2},{"To":"A1","Time":["06:11","23:26"],"TrainType":2}]},{"StationID":"A4","lat":25.059,"lon":25.059,"name":"新莊副都心站","ename":"Xinzhuang Fuduxin Station","FirstLast":[{"To":"A21","Time":["06:05","23:22"],"TrainType":1},{"To":"A1","Time":["06:00","00:09"],"TrainType":1}]},{"StationID":"A5","lat":25.052,"lon":25.052,"name":"泰山站","ename":"Taishan Station","FirstLast":[{"To":"A21","Time":["06:07","23:24"],"TrainType":1},{"To":"A1","Time":["05:58","00:07"],"TrainType":1}]},{"StationID":"A6","lat":25.033,"lon":25.033,"name":"泰山貴和站","ename":"Taishan Guihe Station","FirstLast":[{"To":"A21","Time":["06:10","23:27"],"TrainType":1},{"To":"A1","Time":["06:10","00:04"],"TrainType":1}]},{"StationID":"A7","lat":25.041,"lon":25.041,"name":"體育大學站","ename":"National Taiwan Sport University Station","FirstLast":[{"To":"A21","Time":["06:00","23:32"],"TrainType":1},{"To":"A1","Time":["06:03","23:57"],"TrainType":1}]},{"StationID":"A8","lat":25.061,"lon":25.061,"name":"長庚醫院站","ename":"Chang Gung Memorial Hospital Station","FirstLast":[{"To":"A21","Time":["06:08","23:36"],"TrainType":1},{"To":"A1","Time":["05:59","23:53"],"TrainType":1},{"To":"A13","Time":["06:06","23:21"],"TrainType":2},{"To":"A1","Time":["05:58","23:11"],"TrainType":2}]},{"StationID":"A9","lat":25.066,"lon":25.066,"name":"林口站","ename":"Linkou Station","FirstLast":[{"To":"A21","Time":["06:11","23:39"],"TrainType":1},{"To":"A1","Time":["06:07","23:50"],"TrainType":1}]},{"StationID":"A10","lat":25.081,"lon":25.081,"name":"山鼻站","ename":"Shanbi Station","FirstLast":[{"To":"A21","Time":["06:05","23:48"],"TrainType":1},{"To":"A1","Time":["05:59","23:42"],"TrainType":1}]},{"StationID":"A11","lat":25.086,"lon":25.086,"name":"坑口站","ename":"Kengkou Station","FirstLast":[{"To":"A21","Time":["06:08","23:51"],"TrainType":1},{"To":"A1","Time":["06:11","23:40"],"TrainType":1}]},{"StationID":"A12","lat":25.082,"lon":25.082,"name":"機場第一航廈站","ename":"Airport Terminal 1 Station","FirstLast":[{"To":"A21","Time":["05:57","23:55"],"TrainType":1},{"To":"A1","Time":["06:07","23:36"],"TrainType":1},{"To":"A13","Time":["06:07","23:37"],"TrainType":2},{"To":"A1","Time":["05:59","22:58"],"TrainType":2}]},{"StationID":"A13","lat":25.077,"lon":25.077,"name":"機場第二航廈站","ename":"Airport Terminal 2 Station","FirstLast":[{"To":"A21","Time":["06:00","23:57"],"TrainType":1},{"To":"A1","Time":["06:04","23:33"],"TrainType":1},{"To":"A1","Time":["05:57","22:55"],"TrainType":2}]},{"StationID":"A14a","lat":25.069,"lon":25.069,"name":"機場旅館站","ename":"Airport Hotel Station","FirstLast":[{"To":"A21","Time":["06:03","00:00"],"TrainType":1},{"To":"A1","Time":["06:00","23:29"],"TrainType":1}]},{"StationID":"A15","lat":25.056,"lon":25.056,"name":"大園站","ename":"Dayuan Station","FirstLast":[{"To":"A21","Time":["06:06","00:03"],"TrainType":1},{"To":"A1","Time":["06:12","23:26"],"TrainType":1}]},{"StationID":"A16","lat":25.037,"lon":25.037,"name":"橫山站","ename":"Hengshan Station","FirstLast":[{"To":"A21","Time":["06:09","00:06"],"TrainType":1},{"To":"A1","Time":["06:09","23:23"],"TrainType":1}]},{"StationID":"A17","lat":25.024,"lon":25.024,"name":"領航站","ename":"Linghang Station","FirstLast":[{"To":"A21","Time":["06:12","00:09"],"TrainType":1},{"To":"A1","Time":["06:06","23:20"],"TrainType":1}]},{"StationID":"A18","lat":25.014,"lon":25.014,"name":"高鐵桃園站","ename":"Taoyuan HSR Station","FirstLast":[{"To":"A21","Time":["06:02","00:13"],"TrainType":1},{"To":"A1","Time":["06:02","23:16"],"TrainType":1}]},{"StationID":"A19","lat":25.002,"lon":25.002,"name":"桃園體育園區站","ename":"Taoyuan Sports Park Station","FirstLast":[{"To":"A21","Time":["06:05","00:16"],"TrainType":1},{"To":"A1","Time":["06:13","23:13"],"TrainType":1}]},{"StationID":"A20","lat":24.98,"lon":24.98,"name":"興南站","ename":"Xingnan Station","FirstLast":[{"To":"A21","Time":["06:10","00:21"],"TrainType":1},{"To":"A1","Time":["06:08","23:08"],"TrainType":1}]},{"StationID":"A21","lat":24.967,"lon":24.967,"name":"環北站","ename":"Huanbei Station","FirstLast":[{"To":"A1","Time":["06:05","23:05"],"TrainType":1}]}]